probability_distributions_may2020/Binomialdistribution.py
probability_distributions_may2020/Gaussiandistribution.py
probability_distributions_may2020/Generaldistribution.py
probability_distributions_may2020/__init__.py
probability_distributions_may2020-1.2.2.dist-info/DESCRIPTION.rst
probability_distributions_may2020-1.2.2.dist-info/METADATA
probability_distributions_may2020-1.2.2.dist-info/RECORD
probability_distributions_may2020-1.2.2.dist-info/WHEEL
probability_distributions_may2020-1.2.2.dist-info/metadata.json
probability_distributions_may2020-1.2.2.dist-info/top_level.txt
