Metadata-Version: 2.0
Name: probability-distributions-may2020
Version: 1.2.2
Summary: Gaussian and Binomial distributions
Home-page: UNKNOWN
Author: Aayush Patni
Author-email: UNKNOWN
License: UNKNOWN
Platform: UNKNOWN
